cogflow/__init__.py
cogflow/cogflow_config.ini
cogflow/plugin_config.py
cogflow/pluginerrors.py
cogflow/pluginmanager.py
cogflow/util.py
cogflow/kafka/__init__.py
cogflow/kafka/consumer.py
cogflow/kafka/producer.py
cogflow/plugins/component_plugin.py
cogflow/plugins/dataset_plugin.py
cogflow/plugins/knative_plugin.py
cogflow/plugins/kubeflowplugin.py
cogflow/plugins/message_broker_dataset_plugin.py
cogflow/plugins/mlflowplugin.py
cogflow/plugins/notebook_plugin.py
cogflow/schema/__init__.py
cogflow/schema/message_broker_metadata.py
cogflow/v2/__init__.py
cogflow-1.11.26.dist-info/licenses/LICENSE.md
tests/__init__.py
tests/test_dataset_plugin.py
tests/test_kubeflowplugin.py
tests/test_mlflowplugin.py
tests/test_notebook_plugin.py
tests/test_plugin_manager.py
cogflow-1.11.26.dist-info/METADATA
cogflow-1.11.26.dist-info/WHEEL
cogflow-1.11.26.dist-info/top_level.txt
cogflow-1.11.26.dist-info/RECORD
