Metadata-Version: 2.4
Name: cogflow
Version: 1.11.26
Summary: COG modules
Author: Sai_kireeti
Author-email: sai.kireeti@hiro-microdatacenters.nl
Classifier: Programming Language :: Python :: 3
Classifier: Operating System :: OS Independent
Requires-Python: >=3.10
License-File: LICENSE.md
Requires-Dist: mlflow==2.22.0
Requires-Dist: kfp==1.8.22
Requires-Dist: boto3
Requires-Dist: tenacity
Requires-Dist: pandas
Requires-Dist: numpy==1.24.4
Requires-Dist: kubernetes
Requires-Dist: minio
Requires-Dist: scikit-learn==1.2.0
Requires-Dist: awscli
Requires-Dist: s3fs
Requires-Dist: setuptools==68.2.2
Requires-Dist: kserve==0.12.0
Requires-Dist: shap
Requires-Dist: ray==2.9.3
Requires-Dist: kafka-python==2.0.2
Requires-Dist: pyyaml
Dynamic: author
Dynamic: author-email
Dynamic: classifier
Dynamic: description
Dynamic: description-content-type
Dynamic: license-file
Dynamic: requires-dist
Dynamic: requires-python
Dynamic: summary
